backup_utils/Backup.py
backup_utils/DatabaseTask.py
backup_utils/Notifier.py
backup_utils/Task.py
backup_utils/__init__.py
backup_utils/__main__.py
backup_utils/databases/MysqlDb.py
backup_utils/databases/PostgreDb.py
backup_utils/databases/SqliteDb.py
backup_utils/databases/__init__.py
backup_utils/notifiers/EmailNotifier.py
backup_utils/notifiers/PrintNotifier.py
backup_utils/notifiers/SignalNotifier.py
backup_utils/notifiers/SlackNotifier.py
backup_utils/notifiers/TelegramNotifier.py
backup_utils/notifiers/VonageNotifier.py
backup_utils/notifiers/__init__.py
backup_utils/syncs/RcloneSync.py
backup_utils/syncs/RsyncSync.py
backup_utils/syncs/__init__.py
backup_utils/tasks/BorgTask.py
backup_utils/tasks/TarTask.py
backup_utils/tasks/__init__.py
backup_utils/thirdparty/SignalCli.py
backup_utils/thirdparty/__init__.py
backup_utils/utils.py
backup_utils-2.6.0.dist-info/LICENSE
backup_utils-2.6.0.dist-info/WHEEL
backup_utils-2.6.0.dist-info/METADATA
backup_utils-2.6.0.dist-info/RECORD
