Metadata-Version: 2.1
Name: backup-utils
Version: 2.6.0
Summary: The goal of the project is to simplify backup creation.
Home-page: https://gitlab.com/Oprax/backup-utils
License: MIT
Author: Romain Muller
Author-email: com@oprax.fr
Requires-Python: >=3.6,<4.0
Classifier: Development Status :: 5 - Production/Stable
Classifier: Environment :: Console
Classifier: Intended Audience :: System Administrators
Classifier: License :: OSI Approved :: MIT License
Classifier: Operating System :: POSIX
Classifier: Programming Language :: Python :: 3
Classifier: Programming Language :: Python :: 3.6
Classifier: Programming Language :: Python :: 3.7
Classifier: Programming Language :: Python :: 3.8
Classifier: Programming Language :: Python :: 3.9
Classifier: Topic :: System :: Archiving :: Backup
Requires-Dist: appdirs (>=1.4.4,<2.0.0)
Requires-Dist: docker (>=4.4.0,<5.0.0)
Requires-Dist: requests (>=2.25.1,<3.0.0)
Requires-Dist: vonage (>=2.5.4,<3.0.0)
Project-URL: Documentation, https://backup-utils.readthedocs.io
Project-URL: Repository, https://gitlab.com/Oprax/backup-utils
